MANIFEST.in
README.md
setup.cfg
setup.py
similarityPy/__init__.py
similarityPy.egg-info/PKG-INFO
similarityPy.egg-info/SOURCES.txt
similarityPy.egg-info/dependency_links.txt
similarityPy.egg-info/not-zip-safe
similarityPy.egg-info/pbr.json
similarityPy.egg-info/requires.txt
similarityPy.egg-info/top_level.txt
similarityPy/algorithms/__init__.py
similarityPy/algorithms/find_nearest.py
similarityPy/algorithms/mean.py
similarityPy/algorithms/median.py
similarityPy/algorithms/norm.py
similarityPy/algorithms/standart_deviation.py
similarityPy/algorithms/sum_formula.py
similarityPy/algorithms/variance.py
similarityPy/data_model/__init__.py
similarityPy/data_model/data_model.py
similarityPy/measure/__init__.py
similarityPy/measure/similarity_measure.py
similarityPy/measure/similarity_measure_type.py
similarityPy/measure/boolean_data/__init__.py
similarityPy/measure/boolean_data/dice_dissimilarity.py
similarityPy/measure/boolean_data/jaccard_dissimilarity.py
similarityPy/measure/boolean_data/matching_dissimilarity.py
similarityPy/measure/boolean_data/rogers_tanimoto_dissimilarity.py
similarityPy/measure/boolean_data/russell_rao_dissimilarity.py
similarityPy/measure/boolean_data/sokal_sneath_dissimilarity.py
similarityPy/measure/boolean_data/yule_dissimilarity.py
similarityPy/measure/numerical_data/__init__.py
similarityPy/measure/numerical_data/bray_curtis_distance.py
similarityPy/measure/numerical_data/canberra_distance.py
similarityPy/measure/numerical_data/chessboard_distance.py
similarityPy/measure/numerical_data/correlation_distance.py
similarityPy/measure/numerical_data/cosine_distance.py
similarityPy/measure/numerical_data/euclidean_distance.py
similarityPy/measure/numerical_data/manhattan_distance.py
similarityPy/measure/numerical_data/normalized_squared_euclidean_distance.py
similarityPy/measure/numerical_data/squared_euclidean_distance.py
similarityPy/measure/string_data/__init__.py
similarityPy/measure/string_data/damerau_levenshtein_distance.py
similarityPy/measure/string_data/edit_distance.py
similarityPy/measure/string_data/hamming_distance.py
similarityPy/measure/string_data/needleman_wunsch_similarity.py
similarityPy/measure/string_data/smith_waterman_similarity.py
similarityPy/utils/__init__.py
