Metadata-Version: 1.1
Name: similarityPy
Version: 0.1.3
Summary: Similarity Algorithm (Data Mining) implementation in Python
Home-page: https://github.com/cenkbircanoglu/similarityPy
Author: Cenk Bircanoglu
Author-email: cenk.bircanoglu@gmail.com
License: MIT
Download-URL: https://github.com/cenkbircanoglu/similarityPy/tarball/v0.1.2
Keywords: data mining,distance,similarity,measure,python,statistic
Platform: any
